redisary/__init__.py
redisary/core.py
redisary-0.1.2.dist-info/LICENSE
redisary-0.1.2.dist-info/METADATA
redisary-0.1.2.dist-info/WHEEL
redisary-0.1.2.dist-info/top_level.txt
redisary-0.1.2.dist-info/RECORD
