Metadata-Version: 2.1
Name: redisary
Version: 0.1.2
Summary: Redis as dictionary
Home-page: https://github.com/xurvan/redisary
Author: Xurvan
License: apache-2.0
Download-URL: https://github.com/xurvan/redisary/archive/v0.1.2.zip
Project-URL: Code, https://github.com/xurvan/redisary
Project-URL: Issue tracker, https://github.com/xurvan/redisary/issues
Platform: UNKNOWN
Classifier: Development Status :: 3 - Alpha
Classifier: Intended Audience :: Developers
Classifier: Topic :: Software Development
Classifier: License :: OSI Approved :: Apache Software License
Classifier: Programming Language :: Python :: 3
Requires-Python: >=3.6
Requires-Dist: redis
